MANIFEST.in
README.md
README.rst
setup.py
django_nghelp/__init__.py
django_nghelp/forms.py
django_nghelp.egg-info/PKG-INFO
django_nghelp.egg-info/SOURCES.txt
django_nghelp.egg-info/dependency_links.txt
django_nghelp.egg-info/not-zip-safe
django_nghelp.egg-info/requires.txt
django_nghelp.egg-info/top_level.txt
django_nghelp/widgets/__init__.py
django_nghelp/widgets/base.py
django_nghelp/widgets/md_datepicker.py
django_nghelp/widgets/md_dateselect.py
django_nghelp/widgets/mdcheckbox.py
django_nghelp/widgets/mdmultiselect.py
django_nghelp/widgets/mdselect.py
django_nghelp/widgets/jinja2/attrs.html
django_nghelp/widgets/jinja2/md_checkbox.html
django_nghelp/widgets/jinja2/md_datepicker.html
django_nghelp/widgets/jinja2/md_select.html
django_nghelp/widgets/jinja2/md_select_option.html