Metadata-Version: 1.1
Name: django-nghelp
Version: 2.2.3
Summary: AngularJS Frontend Helper for Django
Home-page: https://github.com/hiroaki-yamamoto/django-nghelp.git
Author: Hiroaki Yamamoto
Author-email: hiroaki@hysoftware.net
License: MIT
Keywords: django AngularJS
Platform: UNKNOWN
Classifier: Development Status :: 7 - Inactive
Classifier: License :: OSI Approved :: MIT License
Classifier: Programming Language :: Python :: 2.7
Classifier: Programming Language :: Python :: 3.5
